Econ_Windows.cp311-win_amd64.pyd
Econ_Windows-0.0.15.dist-info/METADATA
Econ_Windows-0.0.15.dist-info/WHEEL
Econ_Windows-0.0.15.dist-info/top_level.txt
Econ_Windows-0.0.15.dist-info/RECORD
