Metadata-Version: 2.1
Name: Econ-Windows
Version: 0.0.15
Summary: Example project using pybind11
Author: Sulthan Amanu
Author-email: sulthan4380@example.com
